{
  "version": 1,
  "title": "石門國小資訊科技駕駛艙：答題快打 Suno 音樂包",
  "license": "僅放入阿凱老師帳號中可用於本遊戲發布的 Suno Pro／Premier 音檔。",
  "tracks": {
    "lobby": {
      "status": "awaiting-audited-file",
      "path": "assets/audio/smes-it-lobby.mp3",
      "loop": true,
      "volume": 0.28,
      "sunoPrompt": "Instrumental only. Cheerful Taiwanese elementary school technology lab, playful chiptune and marimba, clean synth bass, warm optimistic melody, 100 BPM, seamless 30 second game menu loop, no vocals, no sound effects."
    },
    "battle": {
      "status": "approved",
      "path": "assets/audio/smes-it-battle.mp3",
      "loop": true,
      "volume": 0.32,
      "sunoPrompt": "Instrumental only. Energetic child-friendly cyber classroom battle music, bouncy 8-bit arpeggios, light electronic drums, bright synth lead, playful and focused, 128 BPM, seamless 45 second game loop, no vocals, no aggressive or dark mood.",
      "sunoClipId": "8ef0c939-2a2c-4c37-80ef-91ffb8463aa5",
      "license": "阿凱老師 Suno Pro 帳號產生，可用於本遊戲發布。",
      "durationSeconds": 34.224,
      "sha256": "78B523702A78CBDDCDEAA2B1754FE81B862201FE1BF8F0F0093FBE6B5804B056"
    },
    "ultimate": {
      "status": "approved",
      "path": "assets/audio/smes-it-ultimate.mp3",
      "loop": false,
      "volume": 0.48,
      "sunoPrompt": "Instrumental only. A short 8-second ultimate-combo stinger for a child-friendly technology quiz fighting game: instant bright synth rise, three rhythmic digital impact hits, sparkling chiptune arpeggio, heroic marimba flourish, clean final power chord. Energetic, playful, triumphant, no vocals, no lyrics, no scary or aggressive mood.",
      "sunoClipId": "84753e68-1a90-4061-865c-45e7f5bacd61",
      "license": "阿凱老師 Suno Pro 帳號產生，可用於本遊戲發布。",
      "durationSeconds": 9,
      "sha256": "1A527FB264E8DD3CE26C2BFBDEC9622493F922FF38910DA1D298DE09FA21AC9C"
    },
    "victory": {
      "status": "approved",
      "path": "assets/audio/smes-it-victory.mp3",
      "loop": false,
      "volume": 0.36,
      "sunoPrompt": "Instrumental only. Joyful elementary school coding mission complete theme, uplifting 8-bit melody, marimba and handclaps, proud but gentle, 105 BPM, 12 seconds, no vocals.",
      "sunoClipId": "7b34f804-f60e-43c5-a524-0b5c4db123c8",
      "license": "阿凱老師 Suno Pro 帳號產生，可用於本遊戲發布。",
      "durationSeconds": 43.392,
      "sha256": "5FF4F54BCE0FCE058E1A5D45942ED6C034DF4896145B7D8E84B184DA730A65EE"
    },
    "retry": {
      "status": "awaiting-audited-file",
      "path": "assets/audio/smes-it-retry.mp3",
      "loop": false,
      "volume": 0.28,
      "sunoPrompt": "Instrumental only. Gentle encouraging game retry cue for children, soft electronic bell melody, optimistic rising ending, 8 seconds, no vocals, never sad or scary."
    }
  }
}
